app/__init__.py
app/main.py
data_core_pipelines_beam-0.0.2.dist-info/licenses/LICENSE
src/__init__.py
src/modules/__init__.py
src/modules/wordcount_minimal.py
src/queries/__init__.py
tests/__init__.py
data_core_pipelines_beam-0.0.2.dist-info/METADATA
data_core_pipelines_beam-0.0.2.dist-info/WHEEL
data_core_pipelines_beam-0.0.2.dist-info/top_level.txt
data_core_pipelines_beam-0.0.2.dist-info/RECORD
